LionAPI/__init__.py
LionAPI/app/__init__.py
LionAPI/app/main.py
LionAPI/routers/__init__.py
LionAPI/routers/events.py
LionAPI/services/__init__.py
LionAPI/services/database.py
LionAPI/services/shots.py
LionAPI/services/sofascore_scrapes.py
LionAPI/services/stats.py
LionAPI-0.2.2.dist-info/METADATA
LionAPI-0.2.2.dist-info/WHEEL
LionAPI-0.2.2.dist-info/top_level.txt
LionAPI-0.2.2.dist-info/RECORD
